isfortytwo/__init__.py
isfortytwo/isfortytwo.py
isfortytwo-0.0.11.dist-info/METADATA
isfortytwo-0.0.11.dist-info/WHEEL
isfortytwo-0.0.11.dist-info/top_level.txt
isfortytwo-0.0.11.dist-info/RECORD
