Metadata-Version: 2.1
Name: isfortytwo
Version: 0.0.11
Summary: return if 42
Author: FLAMIE
Author-email: <flamiedev1@gmail.com>
